{
    "version": "230118.37b97ae",
    "source": {
        "channel": "nixpkgs-unstable",
        "revision": "37b97ae3dd714de9a17923d004a2c5b5543dfa6d"
    },
    "platform": {
        "x86_64-darwin": {
            "store": "indices/index-x86_64-darwin",
            "hash": "sha256-bK6JwFamftkrFp3dscjoUrEXa22kx1MOqphM3uNprBI="
        },
        "x86_64-linux": {
            "store": "indices/index-x86_64-linux",
            "hash": "sha256-I+76oNL/0tIgrdBUJYqGS4dPDI6DqsI/AQKWVvJUZRk="
        },
        "i686-linux": {
            "store": "indices/index-i686-linux",
            "hash": "sha256-Is7opJ+EJjYSvqVQiZSA4rK8lX+ItHBCKr04KaRFqec="
        },
        "aarch64-linux": {
            "store": "indices/index-aarch64-linux",
            "hash": "sha256-dym1yvJGqfG5D5gT64KHjBhMor46Xo/efviBatme9QI="
        },
        "aarch64-darwin": {
            "store": "indices/index-aarch64-darwin",
            "hash": "sha256-ATu3tRSFachv/RhRPDvxx7uXYoDDOnPjqBEr97eJCUk="
        }
    }
}
